pulp_cli/__init__.py
pulp_cli/config.py
pulp_cli/generic.py
pulp_cli/py.typed
pulp_cli-0.37.0.dist-info/licenses/LICENSE
pulpcore/cli/ansible/__init__.py
pulpcore/cli/ansible/content.py
pulpcore/cli/ansible/distribution.py
pulpcore/cli/ansible/py.typed
pulpcore/cli/ansible/remote.py
pulpcore/cli/ansible/repository.py
pulpcore/cli/ansible/locale/de/LC_MESSAGES/messages.mo
pulpcore/cli/common/__init__.py
pulpcore/cli/common/acs.py
pulpcore/cli/common/debug.py
pulpcore/cli/common/generic.py
pulpcore/cli/common/i18n.py
pulpcore/cli/common/py.typed
pulpcore/cli/common/locale/de/LC_MESSAGES/messages.mo
pulpcore/cli/container/__init__.py
pulpcore/cli/container/content.py
pulpcore/cli/container/distribution.py
pulpcore/cli/container/namespace.py
pulpcore/cli/container/py.typed
pulpcore/cli/container/remote.py
pulpcore/cli/container/repository.py
pulpcore/cli/container/locale/de/LC_MESSAGES/messages.mo
pulpcore/cli/core/__init__.py
pulpcore/cli/core/access_policy.py
pulpcore/cli/core/artifact.py
pulpcore/cli/core/content.py
pulpcore/cli/core/content_guard.py
pulpcore/cli/core/distribution.py
pulpcore/cli/core/domain.py
pulpcore/cli/core/export.py
pulpcore/cli/core/exporter.py
pulpcore/cli/core/generic.py
pulpcore/cli/core/group.py
pulpcore/cli/core/importer.py
pulpcore/cli/core/orphan.py
pulpcore/cli/core/publication.py
pulpcore/cli/core/py.typed
pulpcore/cli/core/remote.py
pulpcore/cli/core/repository.py
pulpcore/cli/core/role.py
pulpcore/cli/core/show.py
pulpcore/cli/core/signing_service.py
pulpcore/cli/core/status.py
pulpcore/cli/core/task.py
pulpcore/cli/core/task_group.py
pulpcore/cli/core/upload.py
pulpcore/cli/core/upstream_pulp.py
pulpcore/cli/core/user.py
pulpcore/cli/core/vulnerability_report.py
pulpcore/cli/core/worker.py
pulpcore/cli/core/locale/de/LC_MESSAGES/messages.mo
pulpcore/cli/file/__init__.py
pulpcore/cli/file/content.py
pulpcore/cli/file/distribution.py
pulpcore/cli/file/publication.py
pulpcore/cli/file/py.typed
pulpcore/cli/file/remote.py
pulpcore/cli/file/repository.py
pulp_cli-0.37.0.dist-info/METADATA
pulp_cli-0.37.0.dist-info/WHEEL
pulp_cli-0.37.0.dist-info/entry_points.txt
pulp_cli-0.37.0.dist-info/top_level.txt
pulp_cli-0.37.0.dist-info/RECORD
